{
  "verb": [
    {
      "name": "быть",
      "translation": "to be",
      "form": "imperfective",
      "conjugations": {
        "present": {
          "ya": "-",
          "ty": "-",
          "on": "-",
          "my": "-",
          "vy": "-",
          "oni": "-"
        },
        "past": {
          "m": "был",
          "f": "была",
          "n": "было",
          "p": "были"
        },
        "imperative": {
          "ty": "Будь",
          "vy": "Будьте"
        }
      }
    },
    {
      "name": "иметь",
      "translation": "to have",
      "form": "imperfective",
      "conjugations": {
        "present": {
          "ya": "имею",
          "ty": "имеешь",
          "on": "имеет",
          "my": "имеем",
          "vy": "имеете",
          "oni": "имеют"
        },
        "past": {
          "m": "имел",
          "f": "имела",
          "n": "имело",
          "p": "имели"
        },
        "imperative": {
          "ty": "Имей",
          "vy": "Имейте"
        }
      }
    },
    {
      "name": "делать",
      "translation": "to do / to make",
      "form": "imperfective",
      "conjugations": {
        "present": {
          "ya": "делаю",
          "ty": "делаешь",
          "on": "делает",
          "my": "делаем",
          "vy": "делаете",
          "oni": "делают"
        },
        "past": {
          "m": "делал",
          "f": "делала",
          "n": "делало",
          "p": "делали"
        },
        "imperative": {
          "ty": "Делай",
          "vy": "Делайте"
        }
      }
    },
    {
      "name": "сделать",
      "translation": "to do / to make",
      "form": "perfective",
      "conjugations": {
        "present": {
          "ya": "сделаю",
          "ty": "сделаешь",
          "on": "сделает",
          "my": "сделаем",
          "vy": "сделаете",
          "oni": "сделают"
        },
        "past": {
          "m": "сделал",
          "f": "сделала",
          "n": "сделало",
          "p": "сделали"
        },
        "imperative": {
          "ty": "Сделай",
          "vy": "Сделайте"
        }
      }
    },
    {
      "name": "говорить",
      "translation": "to speak / to talk",
      "form": "imperfect",
      "conjugations": {
        "present": {
          "ya": "говорю",
          "ty": "говоришь",
          "on": "говорит",
          "my": "говорим",
          "vy": "говорите",
          "oni": "говорят"
        },
        "past": {
          "m": "говорил",
          "f": "говорила",
          "n": "говорило",
          "p": "говорили"
        },
        "imperative": {
          "ty": "Говори",
          "vy": "Говорите"
        }
      }
    },
    {
      "name": "сказать",
      "translation": "to say / to tell",
      "form": "perfective",
      "conjugations": {
        "present": {
          "ya": "скажу",
          "ty": "скажешь",
          "on": "скажет",
          "my": "скажем",
          "vy": "скажете",
          "oni": "скажут"
        },
        "past": {
          "m": "сказал",
          "f": "сказала",
          "n": "сказало",
          "p": "сказали"
        },
        "imperative": {
          "ty": "Скажи",
          "vy": "Скажите"
        }
      }
    },
    {
      "name": "знать",
      "translation": "to know",
      "form": "imperfective",
      "conjugations": {
        "present": {
          "ya": "знаю",
          "ty": "знаешь",
          "on": "знает",
          "my": "знаем",
          "vy": "знаете",
          "oni": "знают"
        },
        "past": {
          "m": "знал",
          "f": "знала",
          "n": "знало",
          "p": "знали"
        },
        "imperative": {
          "ty": "Знай",
          "vy": "Знайте"
        }
      }
    },
    {
      "name": "узнать",
      "translation": "to learn / to find out / to recognize",
      "form": "perfective",
      "conjugations": {
        "present": {
          "ya": "узнаю",
          "ty": "узнаешь",
          "on": "узнает",
          "my": "узнаем",
          "vy": "узнаете",
          "oni": "узнают"
        },
        "past": {
          "m": "узнал",
          "f": "узнала",
          "n": "узнало",
          "p": "узнали"
        },
        "imperative": {
          "ty": "Узнай",
          "vy": "Узнайте"
        }
      }
    },
    {
      "name": "видеть",
      "translation": "to see",
      "form": "imperfective",
      "conjugations": {
        "present": {
          "ya": "вижу",
          "ty": "видишь",
          "on": "видит",
          "my": "видим",
          "vy": "видите",
          "oni": "видят"
        },
        "past": {
          "m": "видел",
          "f": "видела",
          "n": "видело",
          "p": "видели"
        },
        "imperative": {
          "ty": "Види",
          "vy": "Видите"
        }
      }
    },
    {
      "name": "увидеть",
      "translation": "to see",
      "form": "perfective",
      "conjugations": {
        "present": {
          "ya": "увижу",
          "ty": "увидишь",
          "on": "увидит",
          "my": "увидим",
          "vy": "увидите",
          "oni": "увидят"
        },
        "past": {
          "m": "увидел",
          "f": "увидела",
          "n": "увидело",
          "p": "увидели"
        },
        "imperative": {
          "ty": "Увидь",
          "vy": "Увидьте"
        }
      }
    },
    {
      "name": "идти",
      "translation": "to go (on foot)",
      "form": "imperfective",
      "conjugations": {
        "present": {
          "ya": "иду",
          "ty": "идёшь",
          "on": "идёт",
          "my": "идём",
          "vy": "идёте",
          "oni": "идут"
        },
        "past": {
          "m": "шёл",
          "f": "шла",
          "n": "шло",
          "p": "шли"
        },
        "imperative": {
          "ty": "Иди",
          "vy": "Идите"
        }
      }
    },
    {
      "name": "пойти",
      "translation": "to go (on foot)",
      "form": "perfective",
      "conjugations": {
        "present": {
          "ya": "пойду",
          "ty": "пойдёшь",
          "on": "пойдёт",
          "my": "пойдём",
          "vy": "пойдёте",
          "oni": "пойдут"
        },
        "past": {
          "m": "пошёл",
          "f": "пошла",
          "n": "пошло",
          "p": "пошли"
        },
        "imperative": {
          "ty": "Пойди",
          "vy": "Пойдите"
        }
      }
    },
    {
      "name": "стать",
      "translation": "to become",
      "form": "imperfective",
      "conjugations": {
        "present": {
          "ya": "стану",
          "ty": "станешь",
          "on": "станет",
          "my": "станем",
          "vy": "станете",
          "oni": "станут"
        },
        "past": {
          "m": "стал",
          "f": "стала",
          "n": "стало",
          "p": "стали"
        },
        "imperative": {
          "ty": "Стань",
          "vy": "Станьте"
        }
      }
    },
    {
      "name": "приходить",
      "translation": "to come",
      "form": "imperfective",
      "conjugations": {
        "present": {
          "ya": "прихожу",
          "ty": "приходишь",
          "on": "приходит",
          "my": "приходим",
          "vy": "приходите",
          "oni": "приходят"
        },
        "past": {
          "m": "приходил",
          "f": "приходила",
          "n": "приходило",
          "p": "приходили"
        },
        "imperative": {
          "ty": "Приходи",
          "vy": "Приходите"
        }
      }
    },
    {
      "name": "прийти",
      "translation": "to come / to arrive",
      "form": "perfective",
      "conjugations": {
        "present": {
          "ya": "приду",
          "ty": "придёшь",
          "on": "придёт",
          "my": "придём",
          "vy": "придёте",
          "oni": "придут"
        },
        "past": {
          "m": "пришёл",
          "f": "пришла",
          "n": "пришло",
          "p": "пришли"
        },
        "imperative": {
          "ty": "Приди",
          "vy": "Придите"
        }
      }
    },
    {
      "name": "хотеть",
      "translation": "to want",
      "form": "imperfective",
      "conjugations": {
        "present": {
          "ya": "хочу",
          "ty": "хочешь",
          "on": "хочет",
          "my": "хотим",
          "vy": "хотите",
          "oni": "хотят"
        },
        "past": {
          "m": "хотел",
          "f": "хотела",
          "n": "хотело",
          "p": "хотели"
        },
        "imperative": {
          "ty": "Хочи",
          "vy": "Хотите"
        }
      }
    },
    {
      "name": "работать",
      "translation": "to work",
      "form": "imperfective",
      "conjugations": {
        "present": {
          "ya": "работаю",
          "ty": "работаешь",
          "on": "работает",
          "my": "работаем",
          "vy": "работаете",
          "oni": "работают"
        },
        "past": {
          "m": "работал",
          "f": "работала",
          "n": "работало",
          "p": "работали"
        },
        "imperative": {
          "ty": "Работай",
          "vy": "Работайте"
        }
      }
    },
    {
      "name": "думать",
      "translation": "to think",
      "form": "imperfective",
      "conjugations": {
        "present": {
          "ya": "думаю",
          "ty": "думаешь",
          "on": "думает",
          "my": "думаем",
          "vy": "думаете",
          "oni": "думают"
        },
        "past": {
          "m": "думал",
          "f": "думала",
          "n": "думало",
          "p": "думали"
        },
        "imperative": {
          "ty": "Думай",
          "vy": "Думайте"
        }
      }
    },
    {
      "name": "гулять",
      "translation": "to walk / to stroll",
      "form": "imperfective",
      "conjugations": {
        "present": {
          "ya": "гуляю",
          "ty": "гуляешь",
          "on": "гуляет",
          "my": "гуляем",
          "vy": "гуляете",
          "oni": "гуляют"
        },
        "past": {
          "m": "гулял",
          "f": "гуляла",
          "n": "гуляло",
          "p": "гуляли"
        },
        "imperative": {
          "ty": "Гуляй",
          "vy": "Гуляйте"
        }
      }
    },
    {
      "name": "жить",
      "translation": "to live",
      "form": "imperfective",
      "conjugations": {
        "present": {
          "ya": "живу",
          "ty": "живёшь",
          "on": "живёт",
          "my": "живём",
          "vy": "живёте",
          "oni": "живут"
        },
        "past": {
          "m": "жил",
          "f": "жила",
          "n": "жило",
          "p": "жили"
        },
        "imperative": {
          "ty": "Живи",
          "vy": "Живите"
        }
      }
    },
    {
      "name": "любить",
      "translation": "to love",
      "form": "imperfective",
      "conjugations": {
        "present": {
          "ya": "люблю",
          "ty": "любишь",
          "on": "любит",
          "my": "любим",
          "vy": "любите",
          "oni": "любят"
        },
        "past": {
          "m": "любил",
          "f": "любила",
          "n": "любило",
          "p": "любили"
        },
        "imperative": {
          "ty": "Люби",
          "vy": "Любите"
        }
      }
    },
    {
      "name": "рассказывать",
      "translation": "to tell / to narrate",
      "form": "imperfective",
      "conjugations": {
        "present": {
          "ya": "рассказываю",
          "ty": "рассказываешь",
          "on": "рассказывает",
          "my": "рассказываем",
          "vy": "рассказываете",
          "oni": "рассказывают"
        },
        "past": {
          "m": "рассказывал",
          "f": "рассказывала",
          "n": "рассказывало",
          "p": "рассказывали"
        },
        "imperative": {
          "ty": "Рассказывай",
          "vy": "Рассказывайте"
        }
      }
    },
    {
      "name": "смотреть",
      "translation": "to look / to watch",
      "form": "imperfective",
      "conjugations": {
        "present": {
          "ya": "смотрю",
          "ty": "смотришь",
          "on": "смотрит",
          "my": "смотрим",
          "vy": "смотрите",
          "oni": "смотрят"
        },
        "past": {
          "m": "смотрел",
          "f": "смотрела",
          "n": "смотрело",
          "p": "смотрели"
        },
        "imperative": {
          "ty": "Смотри",
          "vy": "Смотрите"
        }
      }
    },
    {
      "name": "посмотреть",
      "translation": "to look / to watch",
      "form": "perfective",
      "conjugations": {
        "present": {
          "ya": "посмотрю",
          "ty": "посмотришь",
          "on": "посмотрит",
          "my": "посмотрим",
          "vy": "посмотрите",
          "oni": "посмотрят"
        },
        "past": {
          "m": "посмотрел",
          "f": "посмотрела",
          "n": "посмотрело",
          "p": "посмотрели"
        },
        "imperative": {
          "ty": "Посмотри",
          "vy": "Посмотрите"
        }
      }
    },
    {
      "name": "слушать",
      "translation": "to listen",
      "form": "imperfective",
      "conjugations": {
        "present": {
          "ya": "слушаю",
          "ty": "слушаешь",
          "on": "слушает",
          "my": "слушаем",
          "vy": "слушаете",
          "oni": "слушают"
        },
        "past": {
          "m": "слушал",
          "f": "слушала",
          "n": "слушало",
          "p": "слушали"
        },
        "imperative": {
          "ty": "Слушай",
          "vy": "Слушайте"
        }
      }
    },
    {
      "name": "послушать",
      "translation": "to listen",
      "form": "perfective",
      "conjugations": {
        "present": {
          "ya": "послушаю",
          "ty": "послушаешь",
          "on": "послушает",
          "my": "послушаем",
          "vy": "послушаете",
          "oni": "послушают"
        },
        "past": {
          "m": "послушал",
          "f": "послушала",
          "n": "послушало",
          "p": "послушали"
        },
        "imperative": {
          "ty": "Послушай",
          "vy": "Послушайте"
        }
      }
    },
    {
      "name": "спрашивать",
      "translation": "to ask",
      "form": "imperfective",
      "conjugations": {
        "present": {
          "ya": "спрашиваю",
          "ty": "спрашиваешь",
          "on": "спрашивает",
          "my": "спрашиваем",
          "vy": "спрашиваете",
          "oni": "спрашивают"
        },
        "past": {
          "m": "спрашивал",
          "f": "спрашивала",
          "n": "спрашивало",
          "p": "спрашивали"
        },
        "imperative": {
          "ty": "Спрашивай",
          "vy": "Спрашивайте"
        }
      }
    },
    {
      "name": "спросить",
      "translation": "to ask",
      "form": "perfective",
      "conjugations": {
        "present": {
          "ya": "спрошу",
          "ty": "спросишь",
          "on": "спросит",
          "my": "спросим",
          "vy": "спросите",
          "oni": "спросят"
        },
        "past": {
          "m": "спросил",
          "f": "спросила",
          "n": "спросило",
          "p": "спросили"
        },
        "imperative": {
          "ty": "Спроси",
          "vy": "Спросите"
        }
      }
    },
    {
      "name": "начинать",
      "translation": "to begin / to start",
      "form": "imperfective",
      "conjugations": {
        "present": {
          "ya": "начинаю",
          "ty": "начинаешь",
          "on": "начинает",
          "my": "начинаем",
          "vy": "начинаете",
          "oni": "начинают"
        },
        "past": {
          "m": "начинал",
          "f": "начинала",
          "n": "начинало",
          "p": "начинали"
        },
        "imperative": {
          "ty": "Начинай",
          "vy": "Начинайте"
        }
      }
    },
    {
      "name": "начать",
      "translation": "to begin / to start",
      "form": "perfective",
      "conjugations": {
        "present": {
          "ya": "начну",
          "ty": "начнёшь",
          "on": "начнёт",
          "my": "начнём",
          "vy": "начнёте",
          "oni": "начнут"
        },
        "past": {
          "m": "начал",
          "f": "начала",
          "n": "начало",
          "p": "начали"
        },
        "imperative": {
          "ty": "Начни",
          "vy": "Начните"
        }
      }
    },
    {
      "name": "читать",
      "translation": "to read",
      "form": "imperfective",
      "conjugations": {
        "present": {
          "ya": "читаю",
          "ty": "читаешь",
          "on": "читает",
          "my": "читаем",
          "vy": "читаете",
          "oni": "читают"
        },
        "past": {
          "m": "читал",
          "f": "читала",
          "n": "читало",
          "p": "читали"
        },
        "imperative": {
          "ty": "Читай",
          "vy": "Читайте"
        }
      }
    },
    {
      "name": "прочитать",
      "translation": "to read",
      "form": "perfective",
      "conjugations": {
        "present": {
          "ya": "прочитаю",
          "ty": "прочитаешь",
          "on": "прочитает",
          "my": "прочитаем",
          "vy": "прочитаете",
          "oni": "прочитают"
        },
        "past": {
          "m": "прочитал",
          "f": "прочитала",
          "n": "прочитало",
          "p": "прочитали"
        },
        "imperative": {
          "ty": "Прочитай",
          "vy": "Прочитайте"
        }
      }
    },
    {
      "name": "учить",
      "translation": "to learn / to teach",
      "form": "imperfective",
      "conjugations": {
        "present": {
          "ya": "учу",
          "ty": "учишь",
          "on": "учит",
          "my": "учим",
          "vy": "учите",
          "oni": "учат"
        },
        "past": {
          "m": "учил",
          "f": "учила",
          "n": "учило",
          "p": "учили"
        },
        "imperative": {
          "ty": "Учи",
          "vy": "Учите"
        }
      }
    },
    {
      "name": "выучить",
      "translation": "to learn by heart / to memorize",
      "form": "perfective",
      "conjugations": {
        "present": {
          "ya": "выучу",
          "ty": "выучишь",
          "on": "выучит",
          "my": "выучим",
          "vy": "выучите",
          "oni": "выучат"
        },
        "past": {
          "m": "выучил",
          "f": "выучила",
          "n": "выучило",
          "p": "выучили"
        },
        "imperative": {
          "ty": "Выучи",
          "vy": "Выучите"
        }
      }
    },
    {
      "name": "делаться",
      "translation": "to become / to happen",
      "form": "imperfective",
      "conjugations": {
        "present": {
          "ya": "делаюсь",
          "ty": "делаешься",
          "on": "делается",
          "my": "делаемся",
          "vy": "делаетесь",
          "oni": "делаются"
        },
        "past": {
          "m": "делался",
          "f": "делалась",
          "n": "делалось",
          "p": "делались"
        },
        "imperative": {
          "ty": "Делайся",
          "vy": "Делайтесь"
        }
      }
    },
    {
      "name": "сделаться",
      "translation": "to become / to happen",
      "form": "perfective",
      "conjugations": {
        "present": {
          "ya": "сделаюсь",
          "ty": "сделаешься",
          "on": "сделается",
          "my": "сделаемся",
          "vy": "сделаетесь",
          "oni": "сделаются"
        },
        "past": {
          "m": "сделался",
          "f": "сделалась",
          "n": "сделалось",
          "p": "сделались"
        },
        "imperative": {
          "ty": "Сделайся",
          "vy": "Сделайтесь"
        }
      }
    },
    {
      "name": "давать",
      "translation": "to give",
      "form": "imperfective",
      "conjugations": {
        "present": {
          "ya": "даю",
          "ty": "даёшь",
          "on": "даёт",
          "my": "даём",
          "vy": "даёте",
          "oni": "дают"
        },
        "past": {
          "m": "давал",
          "f": "давала",
          "n": "давало",
          "p": "давали"
        },
        "imperative": {
          "ty": "Давай",
          "vy": "Давайте"
        }
      }
    },
    {
      "name": "дать",
      "translation": "to give",
      "form": "perfective",
      "conjugations": {
        "present": {
          "ya": "дам",
          "ty": "дашь",
          "on": "даст",
          "my": "дадим",
          "vy": "дасте",
          "oni": "дадут"
        },
        "past": {
          "m": "дал",
          "f": "дала",
          "n": "дало",
          "p": "дали"
        },
        "imperative": {
          "ty": "Дай",
          "vy": "Дайте"
        }
      }
    },
    {
      "name": "понимать",
      "translation": "to understand",
      "form": "imperfective",
      "conjugations": {
        "present": {
          "ya": "понимаю",
          "ty": "понимаешь",
          "on": "понимает",
          "my": "понимаем",
          "vy": "понимаете",
          "oni": "понимают"
        },
        "past": {
          "m": "понимал",
          "f": "понимала",
          "n": "понимало",
          "p": "понимали"
        },
        "imperative": {
          "ty": "Понимай",
          "vy": "Понимайте"
        }
      }
    },
    {
      "name": "понять",
      "translation": "to understand",
      "form": "perfective",
      "conjugations": {
        "present": {
          "ya": "пойму",
          "ty": "поймёшь",
          "on": "поймёт",
          "my": "поймём",
          "vy": "поймёте",
          "oni": "поймут"
        },
        "past": {
          "m": "понял",
          "f": "поняла",
          "n": "поняло",
          "p": "поняли"
        },
        "imperative": {
          "ty": "Пойми",
          "vy": "Поймите"
        }
      }
    },
    {
      "name": "брать",
      "translation": "to take",
      "form": "imperfective",
      "conjugations": {
        "present": {
          "ya": "беру",
          "ty": "берёшь",
          "on": "берёт",
          "my": "берём",
          "vy": "берёте",
          "oni": "берут"
        },
        "past": {
          "m": "брал",
          "f": "брала",
          "n": "брало",
          "p": "брали"
        },
        "imperative": {
          "ty": "Бери",
          "vy": "Берите"
        }
      }
    },
    {
      "name": "взять",
      "translation": "to take",
      "form": "perfective",
      "conjugations": {
        "present": {
          "ya": "возьму",
          "ty": "возьмёшь",
          "on": "возьмёт",
          "my": "возьмём",
          "vy": "возьмёте",
          "oni": "возьмут"
        },
        "past": {
          "m": "взял",
          "f": "взяла",
          "n": "взяло",
          "p": "взяли"
        },
        "imperative": {
          "ty": "Возьми",
          "vy": "Возьмите"
        }
      }
    },
    {
      "name": "стоять",
      "translation": "to stand",
      "form": "imperfective",
      "conjugations": {
        "present": {
          "ya": "стою",
          "ty": "стоишь",
          "on": "стоит",
          "my": "стоим",
          "vy": "стоите",
          "oni": "стоят"
        },
        "past": {
          "m": "стоял",
          "f": "стояла",
          "n": "стояло",
          "p": "стояли"
        },
        "imperative": {
          "ty": "Стоя",
          "vy": "Стоите"
        }
      }
    },
    {
      "name": "встать",
      "translation": "to stand up",
      "form": "perfective",
      "conjugations": {
        "present": {
          "ya": "встану",
          "ty": "встанешь",
          "on": "встанет",
          "my": "встанем",
          "vy": "встанете",
          "oni": "встанут"
        },
        "past": {
          "m": "встал",
          "f": "встала",
          "n": "встало",
          "p": "встали"
        },
        "imperative": {
          "ty": "Встань",
          "vy": "Встаньте"
        }
      }
    },
    {
      "name": "ждать",
      "translation": "to wait",
      "form": "imperfective",
      "conjugations": {
        "present": {
          "ya": "жду",
          "ty": "ждёшь",
          "on": "ждёт",
          "my": "ждём",
          "vy": "ждёте",
          "oni": "ждут"
        },
        "past": {
          "m": "ждал",
          "f": "ждала",
          "n": "ждало",
          "p": "ждали"
        },
        "imperative": {
          "ty": "Жди",
          "vy": "Ждите"
        }
      }
    },
    {
      "name": "подождать",
      "translation": "to wait (for a while)",
      "form": "perfective",
      "conjugations": {
        "present": {
          "ya": "подожду",
          "ty": "подождешь",
          "on": "подождет",
          "my": "подождем",
          "vy": "подождете",
          "oni": "подождут"
        },
        "past": {
          "m": "подождал",
          "f": "подождала",
          "n": "подождало",
          "p": "подождали"
        },
        "imperative": {
          "ty": "Подожди",
          "vy": "Подождите"
        }
      }
    },
    {
      "name": "оставаться",
      "translation": "to remain / to stay",
      "form": "imperfective",
      "conjugations": {
        "present": {
          "ya": "остаюсь",
          "ty": "остаешься",
          "on": "остается",
          "my": "остаемся",
          "vy": "остаетесь",
          "oni": "остаются"
        },
        "past": {
          "m": "оставался",
          "f": "оставалась",
          "n": "оставалось",
          "p": "оставались"
        },
        "imperative": {
          "ty": "Оставайся",
          "vy": "Оставайтесь"
        }
      }
    },
    {
      "name": "остаться",
      "translation": "to remain / to stay",
      "form": "perfective",
      "conjugations": {
        "present": {
          "ya": "останусь",
          "ty": "останешься",
          "on": "останется",
          "my": "останемся",
          "vy": "останетесь",
          "oni": "останутся"
        },
        "past": {
          "m": "остался",
          "f": "осталась",
          "n": "осталось",
          "p": "остались"
        },
        "imperative": {
          "ty": "Останься",
          "vy": "Останьтесь"
        }
      }
    },
    {
      "name": "играть",
      "translation": "to play",
      "form": "imperfective",
      "conjugations": {
        "present": {
          "ya": "играю",
          "ty": "играешь",
          "on": "играет",
          "my": "играем",
          "vy": "играете",
          "oni": "играют"
        },
        "past": {
          "m": "играл",
          "f": "играла",
          "n": "играло",
          "p": "играли"
        },
        "imperative": {
          "ty": "Играй",
          "vy": "Играйте"
        }
      }
    },
    {
      "name": "показывать",
      "translation": "to show",
      "form": "imperfective",
      "conjugations": {
        "present": {
          "ya": "показываю",
          "ty": "показываешь",
          "on": "показывает",
          "my": "показываем",
          "vy": "показываете",
          "oni": "показывают"
        },
        "past": {
          "m": "показывал",
          "f": "показывала",
          "n": "показывало",
          "p": "показывали"
        },
        "imperative": {
          "ty": "Показывай",
          "vy": "Показывайте"
        }
      }
    },
    {
      "name": "показать",
      "translation": "to show",
      "form": "perfective",
      "conjugations": {
        "present": {
          "ya": "покажу",
          "ty": "покажешь",
          "on": "покажет",
          "my": "покажем",
          "vy": "покажете",
          "oni": "покажут"
        },
        "past": {
          "m": "показал",
          "f": "показала",
          "n": "показало",
          "p": "показали"
        },
        "imperative": {
          "ty": "Покажи",
          "vy": "Покажите"
        }
      }
    },
    {
      "name": "заниматься",
      "translation": "to be engaged in / to occupy oneself with",
      "form": "imperfective",
      "conjugations": {
        "present": {
          "ya": "занимаюсь",
          "ty": "занимаешься",
          "on": "занимается",
          "my": "занимаемся",
          "vy": "занимаетесь",
          "oni": "занимаются"
        },
        "past": {
          "m": "занимался",
          "f": "занималась",
          "n": "занималось",
          "p": "занимались"
        },
        "imperative": {
          "ty": "Занимайся",
          "vy": "Занимайтесь"
        }
      }
    },
    {
      "name": "заняться",
      "translation": "to begin doing / to occupy oneself with",
      "form": "perfective",
      "conjugations": {
        "present": {
          "ya": "займусь",
          "ty": "займёшься",
          "on": "займётся",
          "my": "займёмся",
          "vy": "займётесь",
          "oni": "займутся"
        },
        "past": {
          "m": "занялся",
          "f": "занялась",
          "n": "занялось",
          "p": "занялись"
        },
        "imperative": {
          "ty": "Займись",
          "vy": "Займитесь"
        }
      }
    },
    {
      "name": "спать",
      "translation": "to sleep",
      "form": "imperfective",
      "conjugations": {
        "present": {
          "ya": "сплю",
          "ty": "спишь",
          "on": "спит",
          "my": "спим",
          "vy": "спите",
          "oni": "спят"
        },
        "past": {
          "m": "спал",
          "f": "спала",
          "n": "спало",
          "p": "спали"
        },
        "imperative": {
          "ty": "Спи",
          "vy": "Спите"
        }
      }
    },
    {
      "name": "поспать",
      "translation": "to sleep",
      "form": "perfective",
      "conjugations": {
        "present": {
          "ya": "посплю",
          "ty": "поспишь",
          "on": "поспит",
          "my": "поспим",
          "vy": "поспите",
          "oni": "поспят"
        },
        "past": {
          "m": "поспал",
          "f": "поспала",
          "n": "поспало",
          "p": "поспали"
        },
        "imperative": {
          "ty": "Поспи",
          "vy": "Поспите"
        }
      }
    },
    {
      "name": "слышать",
      "translation": "to hear",
      "form": "imperfective",
      "conjugations": {
        "present": {
          "ya": "слышу",
          "ty": "слышишь",
          "on": "слышит",
          "my": "слышим",
          "vy": "слышите",
          "oni": "слышат"
        },
        "past": {
          "m": "слышал",
          "f": "слышала",
          "n": "слышало",
          "p": "слышали"
        },
        "imperative": {
          "ty": "Слышь",
          "vy": "Слышьте"
        }
      }
    },
    {
      "name": "услышать",
      "translation": "to hear",
      "form": "perfective",
      "conjugations": {
        "present": {
          "ya": "услышу",
          "ty": "услышишь",
          "on": "услышит",
          "my": "услышим",
          "vy": "услышите",
          "oni": "услышат"
        },
        "past": {
          "m": "услышал",
          "f": "услышала",
          "n": "услышало",
          "p": "услышали"
        },
        "imperative": {
          "ty": "Услышь",
          "vy": "Услышьте"
        }
      }
    },
    {
      "name": "ехать",
      "translation": "to go / to ride (by vehicle)",
      "form": "imperfective",
      "conjugations": {
        "present": {
          "ya": "еду",
          "ty": "едешь",
          "on": "едет",
          "my": "едем",
          "vy": "едете",
          "oni": "едут"
        },
        "past": {
          "m": "ехал",
          "f": "ехала",
          "n": "ехало",
          "p": "ехали"
        },
        "imperative": {
          "ty": "Едь",
          "vy": "Езжайте"
        }
      }
    },
    {
      "name": "поехать",
      "translation": "to go / to ride (by vehicle)",
      "form": "perfective",
      "conjugations": {
        "present": {
          "ya": "поеду",
          "ty": "поедешь",
          "on": "поедет",
          "my": "поедем",
          "vy": "поедете",
          "oni": "поедут"
        },
        "past": {
          "m": "поехал",
          "f": "поехала",
          "n": "поехало",
          "p": "поехали"
        },
        "imperative": {
          "ty": "Поезжай",
          "vy": "Поезжайте"
        }
      }
    },
    {
      "name": "помнить",
      "translation": "to remember",
      "form": "imperfective",
      "conjugations": {
        "present": {
          "ya": "помню",
          "ty": "помнишь",
          "on": "помнит",
          "my": "помним",
          "vy": "помните",
          "oni": "помнят"
        },
        "past": {
          "m": "помнил",
          "f": "помнила",
          "n": "помнило",
          "p": "помнили"
        },
        "imperative": {
          "ty": "Помни",
          "vy": "Помните"
        }
      }
    },
    {
      "name": "вспомнить",
      "translation": "to remember / to recall",
      "form": "perfective",
      "conjugations": {
        "present": {
          "ya": "вспомню",
          "ty": "вспомнишь",
          "on": "вспомнит",
          "my": "вспомним",
          "vy": "вспомните",
          "oni": "вспомнят"
        },
        "past": {
          "m": "вспомнил",
          "f": "вспомнила",
          "n": "вспомнило",
          "p": "вспомнили"
        },
        "imperative": {
          "ty": "Вспомни",
          "vy": "Вспомните"
        }
      }
    },
    {
      "name": "держать",
      "translation": "to hold / to keep",
      "form": "imperfective",
      "conjugations": {
        "present": {
          "ya": "держу",
          "ty": "держишь",
          "on": "держит",
          "my": "держим",
          "vy": "держите",
          "oni": "держат"
        },
        "past": {
          "m": "держал",
          "f": "держала",
          "n": "держало",
          "p": "держали"
        },
        "imperative": {
          "ty": "Держи",
          "vy": "Держите"
        }
      }
    },
    {
      "name": "сидеть",
      "translation": "to sit",
      "form": "imperfective",
      "conjugations": {
        "present": {
          "ya": "сижу",
          "ty": "сидишь",
          "on": "сидит",
          "my": "сидим",
          "vy": "сидите",
          "oni": "сидят"
        },
        "past": {
          "m": "сидел",
          "f": "сидела",
          "n": "сидело",
          "p": "сидели"
        },
        "imperative": {
          "ty": "Сиди",
          "vy": "Сидите"
        }
      }
    },
    {
      "name": "сесть",
      "translation": "to sit down",
      "form": "perfective",
      "conjugations": {
        "present": {
          "ya": "сяду",
          "ty": "сядешь",
          "on": "сядет",
          "my": "сядем",
          "vy": "сядете",
          "oni": "сядут"
        },
        "past": {
          "m": "сел",
          "f": "села",
          "n": "село",
          "p": "сели"
        },
        "imperative": {
          "ty": "Сядь",
          "vy": "Сядьте"
        }
      }
    },
    {
      "name": "писать",
      "translation": "to write",
      "form": "imperfective",
      "conjugations": {
        "present": {
          "ya": "пишу",
          "ty": "пишешь",
          "on": "пишет",
          "my": "пишем",
          "vy": "пишете",
          "oni": "пишут"
        },
        "past": {
          "m": "писал",
          "f": "писала",
          "n": "писало",
          "p": "писали"
        },
        "imperative": {
          "ty": "Пиши",
          "vy": "Пишите"
        }
      }
    },
    {
      "name": "написать",
      "translation": "to write",
      "form": "perfective",
      "conjugations": {
        "present": {
          "ya": "напишу",
          "ty": "напишешь",
          "on": "напишет",
          "my": "напишем",
          "vy": "напишете",
          "oni": "напишут"
        },
        "past": {
          "m": "написал",
          "f": "написала",
          "n": "написало",
          "p": "написали"
        },
        "imperative": {
          "ty": "Напиши",
          "vy": "Напишите"
        }
      }
    },
    {
      "name": "закончить",
      "translation": "to finish / to end",
      "form": "perfective",
      "conjugations": {
        "present": {
          "ya": "закончу",
          "ty": "закончишь",
          "on": "закончит",
          "my": "закончим",
          "vy": "закончите",
          "oni": "закончат"
        },
        "past": {
          "m": "закончил",
          "f": "закончила",
          "n": "закончило",
          "p": "закончили"
        },
        "imperative": {
          "ty": "Закончи",
          "vy": "Закончите"
        }
      }
    },
    {
      "name": "продолжать",
      "translation": "to continue",
      "form": "imperfective",
      "conjugations": {
        "present": {
          "ya": "продолжаю",
          "ty": "продолжаешь",
          "on": "продолжает",
          "my": "продолжаем",
          "vy": "продолжаете",
          "oni": "продолжают"
        },
        "past": {
          "m": "продолжал",
          "f": "продолжала",
          "n": "продолжало",
          "p": "продолжали"
        },
        "imperative": {
          "ty": "Продолжай",
          "vy": "Продолжайте"
        }
      }
    },
    {
      "name": "возвращаться",
      "translation": "to return",
      "form": "imperfective",
      "conjugations": {
        "present": {
          "ya": "возвращаюсь",
          "ty": "возвращаешься",
          "on": "возвращается",
          "my": "возвращаемся",
          "vy": "возвращаетесь",
          "oni": "возвращаются"
        },
        "past": {
          "m": "возвращался",
          "f": "возвращалась",
          "n": "возвращалось",
          "p": "возвращались"
        },
        "imperative": {
          "ty": "Возвращайся",
          "vy": "Возвращайтесь"
        }
      }
    },
    {
      "name": "вернуться",
      "translation": "to return",
      "form": "perfective",
      "conjugations": {
        "present": {
          "ya": "вернусь",
          "ty": "вернешься",
          "on": "вернется",
          "my": "вернемся",
          "vy": "вернетесь",
          "oni": "вернутся"
        },
        "past": {
          "m": "вернулся",
          "f": "вернулась",
          "n": "вернулось",
          "p": "вернулись"
        },
        "imperative": {
          "ty": "Вернись",
          "vy": "Вернитесь"
        }
      }
    },
    {
      "name": "верить",
      "translation": "to believe",
      "form": "imperfective",
      "conjugations": {
        "present": {
          "ya": "верю",
          "ty": "веришь",
          "on": "верит",
          "my": "верим",
          "vy": "верите",
          "oni": "верят"
        },
        "past": {
          "m": "верил",
          "f": "верила",
          "n": "верило",
          "p": "верили"
        },
        "imperative": {
          "ty": "Верь",
          "vy": "Верьте"
        }
      }
    },
    {
      "name": "поверить",
      "translation": "to believe",
      "form": "perfective",
      "conjugations": {
        "present": {
          "ya": "поверю",
          "ty": "поверишь",
          "on": "поверит",
          "my": "поверим",
          "vy": "поверите",
          "oni": "поверят"
        },
        "past": {
          "m": "поверил",
          "f": "поверила",
          "n": "поверило",
          "p": "поверили"
        },
        "imperative": {
          "ty": "Поверь",
          "vy": "Поверьте"
        }
      }
    },
    {
      "name": "бывать",
      "translation": "to visit / to be (sometimes)",
      "form": "imperfective",
      "conjugations": {
        "present": {
          "ya": "бываю",
          "ty": "бываешь",
          "on": "бывает",
          "my": "бываем",
          "vy": "бываете",
          "oni": "бывают"
        },
        "past": {
          "m": "бывал",
          "f": "бывала",
          "n": "бывало",
          "p": "бывали"
        },
        "imperative": {
          "ty": "Бывай",
          "vy": "Бывайте"
        }
      }
    },
    {
      "name": "пройти",
      "translation": "to pass / to go through",
      "form": "perfective",
      "conjugations": {
        "present": {
          "ya": "пройду",
          "ty": "пройдёшь",
          "on": "пройдёт",
          "my": "пройдём",
          "vy": "пройдёте",
          "oni": "пройдут"
        },
        "past": {
          "m": "прошёл",
          "f": "прошла",
          "n": "прошло",
          "p": "прошли"
        },
        "imperative": {
          "ty": "Пройди",
          "vy": "Пройдите"
        }
      }
    },
    {
      "name": "нравиться",
      "translation": "to be pleasing / to like",
      "form": "imperfective",
      "conjugations": {
        "present": {
          "ya": "нравлюсь",
          "ty": "нравишься",
          "on": "нравится",
          "my": "нравимся",
          "vy": "нравитесь",
          "oni": "нравятся"
        },
        "past": {
          "m": "нравился",
          "f": "нравилась",
          "n": "нравилось",
          "p": "нравились"
        },
        "imperative": {
          "ty": "Нравься",
          "vy": "Нравьтесь"
        }
      }
    },
    {
      "name": "вести",
      "translation": "to lead / to guide",
      "form": "imperfective",
      "conjugations": {
        "present": {
          "ya": "веду",
          "ty": "ведёшь",
          "on": "ведёт",
          "my": "ведём",
          "vy": "ведёте",
          "oni": "ведут"
        },
        "past": {
          "m": "вёл",
          "f": "вела",
          "n": "вело",
          "p": "вели"
        },
        "imperative": {
          "ty": "Веди",
          "vy": "Ведите"
        }
      }
    },
    {
      "name": "повести",
      "translation": "to lead / to guide",
      "form": "perfective",
      "conjugations": {
        "present": {
          "ya": "поведу",
          "ty": "поведёшь",
          "on": "поведёт",
          "my": "поведём",
          "vy": "поведёте",
          "oni": "поведут"
        },
        "past": {
          "m": "повёл",
          "f": "повела",
          "n": "повело",
          "p": "повели"
        },
        "imperative": {
          "ty": "Поведи",
          "vy": "Поведите"
        }
      }
    },
    {
      "name": "учиться",
      "translation": "to learn",
      "form": "imperfective",
      "conjugations": {
        "present": {
          "ya": "учусь",
          "ty": "учишься",
          "on": "учится",
          "my": "учимся",
          "vy": "учитесь",
          "oni": "учатся"
        },
        "past": {
          "m": "учился",
          "f": "училась",
          "n": "училось",
          "p": "учились"
        },
        "imperative": {
          "ty": "Учись",
          "vy": "Учитесь"
        }
      }
    },
    {
      "name": "научиться",
      "translation": "to learn / to become proficient in",
      "form": "perfective",
      "conjugations": {
        "present": {
          "ya": "научусь",
          "ty": "научишься",
          "on": "научится",
          "my": "научимся",
          "vy": "научитесь",
          "oni": "научатся"
        },
        "past": {
          "m": "научился",
          "f": "научилась",
          "n": "научилось",
          "p": "научились"
        },
        "imperative": {
          "ty": "Научись",
          "vy": "Научитесь"
        }
      }
    },
    {
      "name": "есть",
      "translation": "to eat",
      "form": "imperfective",
      "conjugations": {
        "present": {
          "ya": "ем",
          "ty": "ешь",
          "on": "ест",
          "my": "едим",
          "vy": "едите",
          "oni": "едят"
        },
        "past": {
          "m": "ел",
          "f": "ела",
          "n": "ело",
          "p": "ели"
        },
        "imperative": {
          "ty": "Ешь",
          "vy": "Ешьте"
        }
      }
    },
    {
      "name": "съесть",
      "translation": "to eat",
      "form": "perfective",
      "conjugations": {
        "present": {
          "ya": "съем",
          "ty": "съешь",
          "on": "съест",
          "my": "съедим",
          "vy": "съедите",
          "oni": "съедят"
        },
        "past": {
          "m": "съел",
          "f": "съела",
          "n": "съело",
          "p": "съели"
        },
        "imperative": {
          "ty": "Съешь",
          "vy": "Съешьте"
        }
      }
    },
    {
      "name": "мочь",
      "translation": "can / to be able to",
      "form": "imperfective",
      "conjugations": {
        "present": {
          "ya": "могу",
          "ty": "можешь",
          "on": "может",
          "my": "можем",
          "vy": "можете",
          "oni": "могут"
        },
        "past": {
          "m": "мог",
          "f": "могла",
          "n": "могло",
          "p": "могли"
        },
        "imperative": {
          "ty": "Можешь",
          "vy": "Можете"
        }
      }
    },
    {
      "name": "ходить",
      "translation": "to walk / to go",
      "form": "imperfective",
      "conjugations": {
        "present": {
          "ya": "хожу",
          "ty": "ходишь",
          "on": "ходит",
          "my": "ходим",
          "vy": "ходите",
          "oni": "ходят"
        },
        "past": {
          "m": "ходил",
          "f": "ходила",
          "n": "ходило",
          "p": "ходили"
        },
        "imperative": {
          "ty": "Ходи",
          "vy": "Ходите"
        }
      }
    },
    {
      "name": "пить",
      "translation": "to drink",
      "form": "imperfective",
      "conjugations": {
        "present": {
          "ya": "пью",
          "ty": "пьёшь",
          "on": "пьёт",
          "my": "пьём",
          "vy": "пьёте",
          "oni": "пьют"
        },
        "past": {
          "m": "пил",
          "f": "пила",
          "n": "пило",
          "p": "пили"
        },
        "imperative": {
          "ty": "Пей",
          "vy": "Пейте"
        }
      }
    },
    {
      "name": "выпить",
      "translation": "to drink",
      "form": "perfective",
      "conjugations": {
        "present": {
          "ya": "выпью",
          "ty": "выпьешь",
          "on": "выпьет",
          "my": "выпьем",
          "vy": "выпьете",
          "oni": "выпьют"
        },
        "past": {
          "m": "выпил",
          "f": "выпила",
          "n": "выпило",
          "p": "выпили"
        },
        "imperative": {
          "ty": "Выпей",
          "vy": "Выпейте"
        }
      }
    },
    {
      "name": "ездить",
      "translation": "to ride / to drive",
      "form": "imperfective",
      "conjugations": {
        "present": {
          "ya": "езжу",
          "ty": "ездишь",
          "on": "ездит",
          "my": "ездим",
          "vy": "ездите",
          "oni": "ездят"
        },
        "past": {
          "m": "ездил",
          "f": "ездила",
          "n": "ездило",
          "p": "ездили"
        },
        "imperative": {
          "ty": "Езжай",
          "vy": "Ездите"
        }
      }
    },
    {
      "name": "отдыхать",
      "translation": "to rest / to relax",
      "form": "imperfective",
      "conjugations": {
        "present": {
          "ya": "отдыхаю",
          "ty": "отдыхаешь",
          "on": "отдыхает",
          "my": "отдыхаем",
          "vy": "отдыхаете",
          "oni": "отдыхают"
        },
        "past": {
          "m": "отдыхал",
          "f": "отдыхала",
          "n": "отдыхало",
          "p": "отдыхали"
        },
        "imperative": {
          "ty": "Отдыхай",
          "vy": "Отдыхайте"
        }
      }
    },
    {
      "name": "мыть",
      "translation": "to wash",
      "form": "imperfective",
      "conjugations": {
        "present": {
          "ya": "мою",
          "ty": "моешь",
          "on": "моет",
          "my": "моем",
          "vy": "моете",
          "oni": "моют"
        },
        "past": {
          "m": "мыл",
          "f": "мыла",
          "n": "мыло",
          "p": "мыли"
        },
        "imperative": {
          "ty": "Мой",
          "vy": "Мойте"
        }
      }
    },
    {
      "name": "помыть",
      "translation": "to wash",
      "form": "perfective",
      "conjugations": {
        "present": {
          "ya": "помою",
          "ty": "помоешь",
          "on": "помоет",
          "my": "помоем",
          "vy": "помоете",
          "oni": "помоют"
        },
        "past": {
          "m": "помыл",
          "f": "помыла",
          "n": "помыло",
          "p": "помыли"
        },
        "imperative": {
          "ty": "Помой",
          "vy": "Помойте"
        }
      }
    },
    {
      "name": "помогать",
      "translation": "to help",
      "form": "imperfective",
      "conjugations": {
        "present": {
          "ya": "помогаю",
          "ty": "помогаешь",
          "on": "помогает",
          "my": "помогаем",
          "vy": "помогаете",
          "oni": "помогают"
        },
        "past": {
          "m": "помогал",
          "f": "помогала",
          "n": "помогало",
          "p": "помогали"
        },
        "imperative": {
          "ty": "Помогай",
          "vy": "Помогайте"
        }
      }
    },
    {
      "name": "помочь",
      "translation": "to help",
      "form": "perfective",
      "conjugations": {
        "present": {
          "ya": "помогу",
          "ty": "поможешь",
          "on": "поможет",
          "my": "поможем",
          "vy": "поможете",
          "oni": "помогут"
        },
        "past": {
          "m": "помог",
          "f": "помогла",
          "n": "помогло",
          "p": "помогли"
        },
        "imperative": {
          "ty": "Помоги",
          "vy": "Помогите"
        }
      }
    },
    {
      "name": "изучать",
      "translation": "to study / to learn",
      "form": "imperfective",
      "conjugations": {
        "present": {
          "ya": "изучаю",
          "ty": "изучаешь",
          "on": "изучает",
          "my": "изучаем",
          "vy": "изучаете",
          "oni": "изучают"
        },
        "past": {
          "m": "изучал",
          "f": "изучала",
          "n": "изучало",
          "p": "изучали"
        },
        "imperative": {
          "ty": "Изучай",
          "vy": "Изучайте"
        }
      }
    },
    {
      "name": "изучить",
      "translation": "to study / to learn",
      "form": "perfective",
      "conjugations": {
        "present": {
          "ya": "изучу",
          "ty": "изучишь",
          "on": "изучит",
          "my": "изучим",
          "vy": "изучите",
          "oni": "изучат"
        },
        "past": {
          "m": "изучил",
          "f": "изучила",
          "n": "изучило",
          "p": "изучили"
        },
        "imperative": {
          "ty": "Изучи",
          "vy": "Изучите"
        }
      }
    },
    {
      "name": "петь",
      "translation": "to sing",
      "form": "imperfective",
      "conjugations": {
        "present": {
          "ya": "пою",
          "ty": "поёшь",
          "on": "поёт",
          "my": "поём",
          "vy": "поёте",
          "oni": "поют"
        },
        "past": {
          "m": "пел",
          "f": "пела",
          "n": "пело",
          "p": "пели"
        },
        "imperative": {
          "ty": "Пой",
          "vy": "Пойте"
        }
      }
    },
    {
      "name": "носить",
      "translation": "to carry / to wear",
      "form": "imperfective",
      "conjugations": {
        "present": {
          "ya": "ношу",
          "ty": "носишь",
          "on": "носит",
          "my": "носим",
          "vy": "носите",
          "oni": "носят"
        },
        "past": {
          "m": "носил",
          "f": "носила",
          "n": "носило",
          "p": "носили"
        },
        "imperative": {
          "ty": "Носи",
          "vy": "Носите"
        }
      }
    },
    {
      "name": "надеть",
      "translation": "to put on / to wear",
      "form": "perfective",
      "conjugations": {
        "present": {
          "ya": "надену",
          "ty": "наденешь",
          "on": "наденет",
          "my": "наденем",
          "vy": "наденете",
          "oni": "наденут"
        },
        "past": {
          "m": "надел",
          "f": "надела",
          "n": "надело",
          "p": "надели"
        },
        "imperative": {
          "ty": "Надень",
          "vy": "Наденьте"
        }
      }
    },
    {
      "name": "найти",
      "translation": "to find",
      "form": "perfective",
      "conjugations": {
        "present": {
          "ya": "найду",
          "ty": "найдёшь",
          "on": "найдёт",
          "my": "найдём",
          "vy": "найдёте",
          "oni": "найдут"
        },
        "past": {
          "m": "нашёл",
          "f": "нашла",
          "n": "нашло",
          "p": "нашли"
        },
        "imperative": {
          "ty": "Найди",
          "vy": "Найдите"
        }
      }
    },
    {
      "name": "танцевать",
      "translation": "to dance",
      "form": "imperfective",
      "conjugations": {
        "present": {
          "ya": "танцую",
          "ty": "танцуешь",
          "on": "танцует",
          "my": "танцуем",
          "vy": "танцуете",
          "oni": "танцуют"
        },
        "past": {
          "m": "танцевал",
          "f": "танцевала",
          "n": "танцевало",
          "p": "танцевали"
        },
        "imperative": {
          "ty": "Танцуй",
          "vy": "Танцуйте"
        }
      }
    },
    {
      "name": "звонить",
      "translation": "to call",
      "form": "imperfective",
      "conjugations": {
        "present": {
          "ya": "звоню",
          "ty": "звонишь",
          "on": "звонит",
          "my": "звоним",
          "vy": "звоните",
          "oni": "звонят"
        },
        "past": {
          "m": "звонил",
          "f": "звонила",
          "n": "звонило",
          "p": "звонили"
        },
        "imperative": {
          "ty": "Звони",
          "vy": "Звоните"
        }
      }
    },
    {
      "name": "позвонить",
      "translation": "to call",
      "form": "perfective",
      "conjugations": {
        "present": {
          "ya": "позвоню",
          "ty": "позвонишь",
          "on": "позвонит",
          "my": "позвоним",
          "vy": "позвоните",
          "oni": "позвонят"
        },
        "past": {
          "m": "позвонил",
          "f": "позвонила",
          "n": "позвонило",
          "p": "позвонили"
        },
        "imperative": {
          "ty": "Позвони",
          "vy": "Позвоните"
        }
      }
    },
    {
      "name": "нести",
      "translation": "to carry",
      "form": "imperfective",
      "conjugations": {
        "present": {
          "ya": "ношу",
          "ty": "носишь",
          "on": "носит",
          "my": "носим",
          "vy": "носите",
          "oni": "носят"
        },
        "past": {
          "m": "нёс",
          "f": "несла",
          "n": "несло",
          "p": "несли"
        },
        "imperative": {
          "ty": "Неси",
          "vy": "Несите"
        }
      }
    },
    {
      "name": "покупать",
      "translation": "to buy",
      "form": "imperfective",
      "conjugations": {
        "present": {
          "ya": "покупаю",
          "ty": "покупаешь",
          "on": "покупает",
          "my": "покупаем",
          "vy": "покупаете",
          "oni": "покупают"
        },
        "past": {
          "m": "покупал",
          "f": "покупала",
          "n": "покупало",
          "p": "покупали"
        },
        "imperative": {
          "ty": "Покупай",
          "vy": "Покупайте"
        }
      }
    },
    {
      "name": "купить",
      "translation": "to buy",
      "form": "perfective",
      "conjugations": {
        "present": {
          "ya": "куплю",
          "ty": "купишь",
          "on": "купит",
          "my": "купим",
          "vy": "купите",
          "oni": "купят"
        },
        "past": {
          "m": "купил",
          "f": "купила",
          "n": "купило",
          "p": "купили"
        },
        "imperative": {
          "ty": "Купи",
          "vy": "Купите"
        }
      }
    },
    {
      "name": "лежать",
      "translation": "to lie",
      "form": "imperfective",
      "conjugations": {
        "present": {
          "ya": "лежу",
          "ty": "лежишь",
          "on": "лежит",
          "my": "лежим",
          "vy": "лежите",
          "oni": "лежат"
        },
        "past": {
          "m": "лежал",
          "f": "лежала",
          "n": "лежало",
          "p": "лежали"
        },
        "imperative": {
          "ty": "Лежи",
          "vy": "Лежите"
        }
      }
    },
    {
      "name": "лечь",
      "translation": "to lie down",
      "form": "perfective",
      "conjugations": {
        "present": {
          "ya": "лягу",
          "ty": "ляжешь",
          "on": "ляжет",
          "my": "ляжем",
          "vy": "ляжете",
          "oni": "лягут"
        },
        "past": {
          "m": "лёг",
          "f": "легла",
          "n": "легло",
          "p": "легли"
        },
        "imperative": {
          "ty": "Ляг",
          "vy": "Лягте"
        }
      }
    },
    {
      "name": "вставать",
      "translation": "to stand up",
      "form": "imperfective",
      "conjugations": {
        "present": {
          "ya": "встаю",
          "ty": "встаёшь",
          "on": "встаёт",
          "my": "встаём",
          "vy": "встаёте",
          "oni": "встают"
        },
        "past": {
          "m": "вставал",
          "f": "вставала",
          "n": "вставало",
          "p": "вставали"
        },
        "imperative": {
          "ty": "Вставай",
          "vy": "Вставайте"
        }
      }
    },
    {
      "name": "готовить",
      "translation": "to prepare / to cook",
      "form": "imperfective",
      "conjugations": {
        "present": {
          "ya": "готовлю",
          "ty": "готовишь",
          "on": "готовит",
          "my": "готовим",
          "vy": "готовите",
          "oni": "готовят"
        },
        "past": {
          "m": "готовил",
          "f": "готовила",
          "n": "готовило",
          "p": "готовили"
        },
        "imperative": {
          "ty": "Готовь",
          "vy": "Готовьте"
        }
      }
    },
    {
      "name": "приготовить",
      "translation": "to prepare / to cook",
      "form": "perfective",
      "conjugations": {
        "present": {
          "ya": "приготовлю",
          "ty": "приготовишь",
          "on": "приготовит",
          "my": "приготовим",
          "vy": "приготовите",
          "oni": "приготовят"
        },
        "past": {
          "m": "приготовил",
          "f": "приготовила",
          "n": "приготовило",
          "p": "приготовили"
        },
        "imperative": {
          "ty": "Приготовь",
          "vy": "Приготовьте"
        }
      }
    },
    {
      "name": "пытаться",
      "translation": "to attempt",
      "form": "imperfective",
      "conjugations": {
        "present": {
          "ya": "пытаюсь",
          "ty": "пытаешься",
          "on": "пытается",
          "my": "пытаемся",
          "vy": "пытаетесь",
          "oni": "пытаются"
        },
        "past": {
          "m": "пытался",
          "f": "пыталась",
          "n": "пыталось",
          "p": "пытались"
        },
        "imperative": {
          "ty": "Пытайся",
          "vy": "Пытайтесь"
        }
      }
    },
    {
      "name": "пытаться",
      "translation": "to attempt",
      "form": "imperfective",
      "conjugations": {
        "present": {
          "ya": "пытаюсь",
          "ty": "пытаешься",
          "on": "пытается",
          "my": "пытаемся",
          "vy": "пытаетесь",
          "oni": "пытаются"
        },
        "past": {
          "m": "пытался",
          "f": "пыталась",
          "n": "пыталось",
          "p": "пытались"
        },
        "imperative": {
          "ty": "Пытайся",
          "vy": "Пытайтесь"
        }
      }
    },
    {
      "name": "попытаться",
      "translation": "to attempt",
      "form": "perfective",
      "conjugations": {
        "present": {
          "ya": "попытаюсь",
          "ty": "попытаешься",
          "on": "попытается",
          "my": "попытаемся",
          "vy": "попытаетесь",
          "oni": "попытаются"
        },
        "past": {
          "m": "попытался",
          "f": "попыталась",
          "n": "попыталось",
          "p": "попытались"
        },
        "imperative": {
          "ty": "Попытайся",
          "vy": "Попытайтесь"
        }
      }
    },
    {
      "name": "смеяться",
      "translation": "to laugh at somebody/something",
      "form": "imperfective",
      "conjugations": {
        "present": {
          "ya": "смеюсь",
          "ty": "смеёшься",
          "on": "смеётся",
          "my": "смеёмся",
          "vy": "смеётесь",
          "oni": "смеются"
        },
        "past": {
          "m": "смеялся",
          "f": "смеялась",
          "n": "смеялось",
          "p": "смеялись"
        },
        "imperative": {
          "ty": "Смейся",
          "vy": "Смейтесь"
        }
      }
    }
  ]
}
